ps_database/__init__.py
ps_database/database code.py
pr_db_connection-0.0.2.dist-info/METADATA
pr_db_connection-0.0.2.dist-info/WHEEL
pr_db_connection-0.0.2.dist-info/top_level.txt
pr_db_connection-0.0.2.dist-info/RECORD
